{
	"format_version": "1.19.0",
	"minecraft:recipe_shapeless": {
		"description": {
			"identifier": "bt:mud_bricks.from_stair"
		},
		"tags": ["crafting_table"],
		"priority": 0,
		"ingredients": [
			{
				"item": "minecraft:mud_brick_stairs"
			},
			{
				"item": "minecraft:mud_brick_stairs"
			},
			{
				"item": "minecraft:mud_brick_stairs"
			},
			{
				"item": "minecraft:mud_brick_stairs"
			}
		],
		"result": {
			"item": "minecraft:mud_bricks",
			"count": 3
		},
		"group": "stairs_to_block"
	}
}
